{
  "BecauseYouWatched": "Porque viu {0}",
  "ContinueWatching": "Continuar a ver",
  "ContinueWatchingNextUp": "Continuar a ver / A seguir",
  "DirectedBy": "Realizado por {0}",
  "Discover": "Descobrir",
  "DiscoverMovies": "Descobrir filmes",
  "DiscoverTV": "Descobrir séries",
  "Genre": "Filmes de {0}",
  "LatestAlbums": "Álbuns mais recentes",
  "LatestAudioBooks": "Audiolivros mais recentes",
  "LatestBooks": "Livros mais recentes",
  "LatestMovies": "Filmes mais recentes",
  "LatestMusicVideo": "Videoclipes mais recentes",
  "LatestShows": "Séries mais recentes",
  "LiveTV": "TV em direto",
  "MyJellyseerrRequests": "Os meus pedidos",
  "MyList": "A minha lista",
  "MyMedia": "Os meus conteúdos",
  "NextUp": "A seguir",
  "RecentlyAddedAlbums": "Álbuns adicionados recentemente",
  "RecentlyAddedArtists": "Artistas adicionados recentemente",
  "RecentlyAddedAudioBooks": "Audiolivros adicionados recentemente",
  "RecentlyAddedBooks": "Livros adicionados recentemente",
  "RecentlyAddedMovies": "Filmes adicionados recentemente",
  "RecentlyAddedMusicVideos": "Videoclipes adicionados recentemente",
  "RecentlyAddedShows": "Séries adicionadas recentemente",
  "Starring": "Com {0}",
  "TopTen": "Top 10",
  "UpcomingBooks": "Livros a estrear",
  "UpcomingMovies": "Filmes a estrear",
  "UpcomingMusic": "Música a estrear",
  "UpcomingShows": "Séries a estrear",
  "WatchAgain": "Ver novamente",

  "Action": "Ação",
  "Adventure": "Aventura",
  "Animation": "Animação",
  "Biography": "Biografia",
  "Comedy": "Comédia",
  "Crime": "Crime",
  "Documentary": "Documentário",
  "Drama": "Drama",
  "Family": "Família",
  "Fantasy": "Fantasia",
  "Food": "Culinária",
  "GameShow": "Programa de jogos",
  "History": "História",
  "Horror": "Terror",
  "Lifestyle": "Estilo de vida",
  "MiniSeries": "Minissérie",
  "Music": "Música",
  "Mystery": "Mistério",
  "Reality": "Reality",
  "RealityTV": "Reality show",
  "Romance": "Romance",
  "ScienceFiction": "Ficção científica",
  "SciFi": "Sci-Fi",
  "Short": "Curta-metragem",
  "Soap": "Telenovela",
  "Sport": "Desporto",
  "Suspense": "Suspense",
  "TalkShow": "Talk-show",
  "Thriller": "Thriller",
  "TVMovie": "Filme para televisão",
  "War": "Guerra",
  "Western": "Western"
}